AbdurrahmanLib/Fibo.py
AbdurrahmanLib/__init__.py
FibApo-0.0.1.dist-info/METADATA
FibApo-0.0.1.dist-info/WHEEL
FibApo-0.0.1.dist-info/top_level.txt
FibApo-0.0.1.dist-info/RECORD
